nbs_bl/__init__.py
nbs_bl/beamline.py
nbs_bl/configuration.py
nbs_bl/detectors.py
nbs_bl/gGrEqns.py
nbs_bl/help.py
nbs_bl/hw.py
nbs_bl/load.py
nbs_bl/motors.py
nbs_bl/planStatus.py
nbs_bl/printing.py
nbs_bl/queueserver.py
nbs_bl/redisDevice.py
nbs_bl/run_engine.py
nbs_bl/samples.py
nbs_bl/settings.py
nbs_bl/shutters.py
nbs_bl/startup.py
nbs_bl/status.py
nbs_bl/utils.py
nbs_bl/devices/__init__.py
nbs_bl/devices/detectors.py
nbs_bl/devices/motors.py
nbs_bl/devices/sampleholders.py
nbs_bl/devices/shutters.py
nbs_bl/devices/slits.py
nbs_bl/geometry/__init__.py
nbs_bl/geometry/affine.py
nbs_bl/geometry/bars.py
nbs_bl/geometry/frames.py
nbs_bl/geometry/linalg.py
nbs_bl/geometry/polygons.py
nbs_bl/plans/__init__.py
nbs_bl/plans/batches.py
nbs_bl/plans/conditions.py
nbs_bl/plans/flyscan_base.py
nbs_bl/plans/groups.py
nbs_bl/plans/maximizers.py
nbs_bl/plans/metaplans.py
nbs_bl/plans/plan_stubs.py
nbs_bl/plans/preprocessors.py
nbs_bl/plans/scan_base.py
nbs_bl/plans/scan_decorators.py
nbs_bl/plans/scans.py
nbs_bl/plans/suspenders.py
nbs_bl/plans/time_estimation.py
nbs_bl/plans/xas.py
nbs_bl/qt/models/beamline.py
nbs_bl/qt/models/energy.py
nbs_bl/qt/widgets/energy.py
nbs_bl/sim/__init__.py
nbs_bl/sim/energy.py
nbs_bl/sim/manipulator.py
nbs_bl/sim/utils.py
nbs_bl/sim/config/polphase.nc
nbs_bl/tests/__init__.py
nbs_bl/tests/modify_regions.py
nbs_bl/tests/test_frames.py
nbs_bl/tests/test_panels.py
nbs_bl-0.2.0.dist-info/METADATA
nbs_bl-0.2.0.dist-info/WHEEL
nbs_bl-0.2.0.dist-info/entry_points.txt
nbs_bl-0.2.0.dist-info/licenses/LICENSE
nbs_bl-0.2.0.dist-info/RECORD
