Metadata-Version: 2.4
Name: nbs-bl
Version: 0.2.0
Summary: NBS Beamline Framework
Project-URL: homepage, https://github.com/xraygui/nbs-bl
Author-email: Charles Titus <ctitus@bnl.gov>
License-File: LICENSE
Keywords: beamline,bluesky,nsls-ii
Classifier: Intended Audience :: Science/Research
Classifier: License :: Public Domain
Classifier: Operating System :: OS Independent
Classifier: Programming Language :: Python :: 3
Requires-Python: >=3.9
Requires-Dist: bluesky
Requires-Dist: bluesky-queueserver
Requires-Dist: databroker>=2.0.0b67
Requires-Dist: ipython
Requires-Dist: nbs-core>=0.1
Requires-Dist: numpy
Requires-Dist: numpydoc
Requires-Dist: ophyd
Requires-Dist: redis-json-dict
Requires-Dist: tomli; python_version < '3.11'
